426 - VLSI SYSTEMS/HW/HW2 (finished)/Q5/MinTermRealization.v
// Chase Lotito - SIUC - SP2024
// ECE426 - Chao Lu
// HW 2 - Q5 - MIN(0,2,4,6,9,10,13,15)

// Using a KMAP we get OUT(A,B,C,D) = A'D' + AC'D + B'CD' + ABD

module MinTermRealization (
    OUT, IN
);

// I/O
input [3:0] IN; // the vector is flipped, I = [D, C, B, A]
output OUT;

// Connecting signals
wire and0, and1, and2, and3;
wire [3:0] _IN;

// Gate-level design
not NOT0(_IN[0], IN[0]);
not NOT1(_IN[1], IN[1]);
not NOT2(_IN[2], IN[2]);
not NOT3(_IN[3], IN[3]);

and AND0(and0, _IN[3], _IN[0]); // Level 1
and AND1(and1, IN[3], _IN[1], IN[0]);
and AND2(and2, _IN[2], IN[1], _IN[0]);
and AND3(and3, IN[3], IN[2], IN[0]);

or OR0(OUT, and0, and1, and2, and3); // OUTPUT

endmodule

426 - VLSI SYSTEMS/HW/HW2 (finished)/Q5/tb.v
// Lotito - Q5 - Testbench

`include "MinTermRealization.v"
`timescale 1ns/1ns

module tb();

// I/O
reg [3:0] IN;
wire OUT;

// GTKWAVE
initial begin : GTKWAVE
    $dumpfile("tb.vcd");
    $dumpvars(0, tb);
end

initial begin : stim
    reg [4:0] iv; // one extra bit so we catch when it overflows
    // Send all 16 inputs to circuit
    for(iv = 0; iv < 16; iv = iv + 1)
        #20 IN = iv;
    #20 $finish;
end

// Instantiate module
MinTermRealization U1 (
    .OUT(OUT), .IN(IN)
);

// CONSOLE LOG
always @(IN or OUT) begin
    $monitor("INPUT = {%b}, MINTERM = %d, OUT = %b", IN, IN, OUT);
end

endmodule

426 - VLSI SYSTEMS/HW/HW2 (finished)/Q5/tb.vcd
$date
	Fri Feb 02 17:12:45 2024
$end
$version
	Icarus Verilog
$end
$timescale
	1ns
$end
$scope module tb $end
$var wire 1 ! OUT $end
$var reg 4 " IN [3:0] $end
$scope module U1 $end
$var wire 4 # IN [3:0] $end
$var wire 1 ! OUT $end
$var wire 1 $ and0 $end
$var wire 1 % and1 $end
$var wire 1 & and2 $end
$var wire 1 ' and3 $end
$var wire 4 ( _IN [3:0] $end
$upscope $end
$scope begin GTKWAVE $end
$upscope $end
$scope begin stim $end
$var reg 5 ) iv [4:0] $end
$upscope $end
$upscope $end
$enddefinitions $end
$comment Show the parameter values. $end
$dumpall
$end
#0
$dumpvars
b0 )
bx (
x'
x&
x%
x$
bx #
bx "
x!
$end
#20
1!
1$
b1111 (
0%
0&
0'
b1 )
b0 "
b0 #
#40
0!
0$
b1110 (
b10 )
b1 "
b1 #
#60
1!
1$
1&
b1101 (
b11 )
b10 "
b10 #
#80
0!
0$
0&
b1100 (
b100 )
b11 "
b11 #
#100
1!
1$
b1011 (
b101 )
b100 "
b100 #
#120
0!
0$
b1010 (
b110 )
b101 "
b101 #
#140
1!
1$
b1001 (
b111 )
b110 "
b110 #
#160
0!
0$
b1000 (
b1000 )
b111 "
b111 #
#180
b111 (
b1001 )
b1000 "
b1000 #
#200
1!
b110 (
1%
b1010 )
b1001 "
b1001 #
#220
1&
1!
b101 (
0%
b1011 )
b1010 "
b1010 #
#240
0!
0&
b100 (
b1100 )
b1011 "
b1011 #
#260
b11 (
b1101 )
b1100 "
b1100 #
#280
1!
b10 (
1%
1'
b1110 )
b1101 "
b1101 #
#300
0!
b1 (
0%
0'
b1111 )
b1110 "
b1110 #
#320
1!
b0 (
1'
b10000 )
b1111 "
b1111 #
