426 - VLSI SYSTEMS/EXAMPREP/final/q4/fsm.v
/*
    Chase Lotito - ECE426 Final Exam Revisions
    Q4 - Design a Moore FSM where '101' input sequence give output of 1
         (X is input and Y is output)
*/

`timescale 1us / 1us

module fsm(clk, x, y);

// i/o
input clk, x;
output y;

reg[1:0] state;

parameter [1:0] A = 2'b00;
parameter [1:0] B = 2'b01;
parameter [1:0] C = 2'b10;

initial state = A;

always @ (posedge clk) begin
    case(state)
        A : state = x ? B : A;
        B : state = x ? C : B;
        C : state = x ? A : C;
        default : state <= 2'bxx;   // something wrong occurred.
    endcase
end

assign y = (state == C);

endmodule

426 - VLSI SYSTEMS/EXAMPREP/final/q4/tb.v
/*
    fsm.v testbench
*/

`timescale 1us / 1us
`include "./fsm.v"

module tb();

initial begin : GTKWAVE
    $dumpfile("tb.vcd");
    $dumpvars(0, tb);
end

// i/o
reg clk, x;
wire y;

// initialize fsm
fsm u1 (
    .clk(clk),
    .x(x),
    .y(y)
);

// initial conditions
initial begin : start
    clk = 0;
    x = 0;
end

// clk
always #10 clk = ~clk;

initial begin : stimulus
    #5 x = 1;
    #10 x = 0;
    #10 x = 1;
    #50 $finish;
end

endmodule

426 - VLSI SYSTEMS/EXAMPREP/final/q4/tb.vcd
$date
	Tue May 07 13:18:39 2024
$end
$version
	Icarus Verilog
$end
$timescale
	1us
$end
$scope module tb $end
$var wire 1 ! y $end
$var reg 1 " clk $end
$var reg 1 # x $end
$scope module u1 $end
$var wire 1 " clk $end
$var wire 1 # x $end
$var wire 1 ! y $end
$var parameter 2 $ A $end
$var parameter 2 % B $end
$var parameter 2 & C $end
$var reg 2 ' state [1:0] $end
$upscope $end
$scope begin GTKWAVE $end
$upscope $end
$scope begin start $end
$upscope $end
$scope begin stimulus $end
$upscope $end
$upscope $end
$enddefinitions $end
$comment Show the parameter values. $end
$dumpall
b10 &
b1 %
b0 $
$end
#0
$dumpvars
b0 '
0#
0"
0!
$end
#5
1#
#10
b1 '
1"
#15
0#
#20
0"
#25
1#
#30
1!
b10 '
1"
#40
0"
#50
0!
b0 '
1"
#60
0"
#70
b1 '
1"
