426 - VLSI SYSTEMS/HW/HW5/q1/q1.v
// Chase Lotito - SIUC Undergraduate - Spring 2024
// ECE426 w/ Chao Lu
// HW5
// Q1: Design a Mealy-type FSM that cdan act as a sequence detector.

`timescale 1us / 1us

module mealyFSM (
    clk, reset, w, out
);

// I/O
input clk, reset, w;
output out;             // wire for continuous assignment

reg [1:0] present, next; // p for present-state, n for next-state

// Parameters for cases
// 3 cases, so lets use 2-bits
parameter A = 2'b01, B = 2'b10, C = 2'b11;  // we will count 1, 2, 3 
// Initial Conditions
initial begin
    present = A;
end

// Console log
always @ (w, out) begin
    $monitor("[PRESENT] = %d | [NEXT] = %d, w = %b | [OUTPUT] = %b \n", present, next, w, out);
end

// Next-State Combinational Logic
always @ (w, present) begin
    case (present)
        A: next = w ? C : B;
        B: next = w ? C : B;
        C: next = w ? C : B;
        default: next = 2'bxx;
    endcase
end

// Sequential Logic
// using posedge reset because not specified in problem statement.
always @ (posedge clk, posedge reset) begin
    if (reset == 1'b1)
        present <= A;
    else
        present <= next;
end

// Output Logic
assign out = ( (present == B) && (w == 1'b0) ) || ( (present == C) && (w == 1'b1) );

endmodule

426 - VLSI SYSTEMS/HW/HW5 (finished)/q1/tb.v
// Chase Lotito - SIUC Undergraduate - Spring 2024
// ECE426 w/ Chao Lu
// HW5
// testbench for Q1


`include "q1.v"
`timescale 1us / 1us

module testbench();

// GTKWAVE
initial begin : GTKWAVE
    $dumpfile("q1.vcd");
    $dumpvars(0, testbench);
end

// I/O
wire out;
reg reset, clk, w;

// Initial Conditions
initial begin : initalConditions
    clk = 0;
    reset = 0;
    w = 0;
end

// Clock
always begin
    #10 clk = ~clk;
end

// Stimulus
initial begin : Stimulus
    repeat(20)
        w = #10 ~w;

    reset <= #50 1'b1;
    #100 $finish;
end

// Instantiate the FSM
mealyFSM U1 (
    .clk(clk),
    .reset(reset),
    .w(w),
    .out(out)
);

endmodule

426 - VLSI SYSTEMS/HW/HW5/q1/q1_mealy.vcd
$date
	Fri Mar 08 15:45:55 2024
$end
$version
	Icarus Verilog
$end
$timescale
	1us
$end
$scope module testbench $end
$scope module U1 $end
$var wire 1 ! clk $end
$var wire 1 " out $end
$var wire 1 # reset $end
$var wire 1 $ w $end
$var parameter 2 % A $end
$var parameter 2 & B $end
$var parameter 2 ' C $end
$var reg 2 ( next [1:0] $end
$var reg 2 ) present [1:0] $end
$scope begin GTKWAVE $end
$upscope $end
$upscope $end
$upscope $end
$scope module testbench $end
$var wire 1 " out $end
$var reg 1 ! clk $end
$var reg 1 # reset $end
$var reg 1 $ w $end
$scope module U1 $end
$scope begin GTKWAVE $end
$upscope $end
$upscope $end
$scope begin GTKWAVE $end
$upscope $end
$scope begin Stimulus $end
$upscope $end
$scope begin initalConditions $end
$upscope $end
$upscope $end
$enddefinitions $end
$comment Show the parameter values. $end
$dumpall
b10 '
b1 &
b0 %
$end
#0
$dumpvars
b0 )
b1 (
0$
0#
0"
0!
$end
#5
b10 (
1$
#10
b10 )
b1 (
0$
1!
#15
1"
b10 (
1$
#20
0"
b1 (
0$
0!
#25
1"
b10 (
1$
#30
0"
b1 (
0$
1!
#35
1"
b10 (
1$
#40
0"
b1 (
0$
0!
#45
1"
b10 (
1$
#50
0"
b1 (
0$
1!
#55
1"
b10 (
1$
#60
0"
b1 (
0$
0!
#65
1"
b10 (
1$
#70
0"
b1 (
0$
1!
#75
1"
b10 (
1$
#80
0"
b1 (
0$
0!
#85
1"
b10 (
1$
#90
0"
b1 (
0$
1!
#95
1"
b10 (
1$
#100
0"
b1 (
0$
0!
#110
1"
b1 )
1!
