426 - VLSI SYSTEMS/LABS/LAB5/src/rom_a.v
/*
    Chase Lotito - SIUC
    ECE426 - Lab 5 - Design of Memory in Verilog
    Section A: ROM Squaring Circuit
        -> square unsigned 0-15
        -> square signed -8-7
*/

module rom_a (n, sign, square);

// I/O
input [3:0] n;             // signed number
input sign;                // bit (1 = signed) (0 = unsigned)
output reg [7:0] square;   // answer = n**2

// procedural block to compute squares as inputs come in
always @ (n or sign)
begin
    if (sign == 1'b0)
    begin
        case (n)           // UNSIGNED
            0 :square <= 0;
            1 :square <= 1;
            2 :square <= 4;
            3 :square <= 9;
            4 :square <= 16;
            5 :square <= 25;
            6 :square <= 36;
            7 :square <= 49;
            8 :square <= 64;
            9 :square <= 81;
            10 :square <= 100;
            11 :square <= 121;
            12 :square <= 144;
            13 :square <= 169;
            14 :square <= 196;
            15 :square <= 225;
            default: square <= 1'bx; // invalid input
        endcase
    end
    else
    begin
        case(n)             // SIGNED
            0 :square <= 0;
            1 :square <= 1;
            2 :square <= 4;
            3 :square <= 9;
            4 :square <= 16;
            5 :square <= 25;
            6 :square <= 36;
            7 :square <= 49;
            8 :square <= 64; // -8 x -8
            9 :square <= 49;
            10 :square <= 36;
            11 :square <= 25;
            12 :square <= 16;
            13 :square <= 9;
            14 :square <= 4;
            15 :square <= 1;
            default: square <= 1'bx; // invalid input
        endcase
    end
end

endmodule

426 - VLSI SYSTEMS/LABS/LAB5/src/rom_a_tb.v
/*
    chase lotito
    lab 5 section a
    rom squarer testbench
*/

`include "./rom_a.v"
`timescale 1us / 1us

module rom_a_tb();

// GTKWAVE (waveform simulator)
initial begin : GTKWAVE
    $dumpfile("rom_a.vcd");
    $dumpvars(0, rom_a_tb);
end

// I/O
reg [3:0] n;             // signed number
reg sign;                // bit (1 = signed) (0 = unsigned)
wire [7:0] square;   // answer = n**2

// Initialize the Squarer ROM
rom_a U1 (
    .n(n), .sign(sign), .square(square)
);

// Send 4-bit numbers 0000 -> 1111
initial begin : stimulus

    // begin sim with unsigned numbers
    sign = 0;

    // n = 0000 -> 1111
    for(integer i = 0; i < 16; i = i + 1)
        #10 n = i;

    #10 n = 0;      // reset n
    sign = 1;   // flip to signed
    #20;        // small delay til next loop

    // n = 0000 -> 1111
    for(integer i = 0; i < 16; i = i + 1)
        #10 n = i;

    #10 $finish;
end


endmodule

426 - VLSI SYSTEMS/LABS/LAB5/src/rom_a.vcd
$date
	Fri Apr 19 21:42:42 2024
$end
$version
	Icarus Verilog
$end
$timescale
	1us
$end
$scope module rom_a_tb $end
$var wire 8 ! square [7:0] $end
$var reg 4 " n [3:0] $end
$var reg 1 # sign $end
$scope module U1 $end
$var wire 4 $ n [3:0] $end
$var wire 1 # sign $end
$var reg 8 % square [7:0] $end
$upscope $end
$scope begin GTKWAVE $end
$upscope $end
$scope begin stimulus $end
$scope begin $ivl_for_loop0 $end
$var integer 32 & i [31:0] $end
$upscope $end
$scope begin $ivl_for_loop1 $end
$var integer 32 ' i [31:0] $end
$upscope $end
$upscope $end
$upscope $end
$enddefinitions $end
$comment Show the parameter values. $end
$dumpall
$end
#0
$dumpvars
bx '
b0 &
b0x %
bx $
0#
bx "
b0x !
$end
#10
b0 !
b0 %
b1 &
b0 "
b0 $
#20
b1 !
b1 %
b10 &
b1 "
b1 $
#30
b100 !
b100 %
b11 &
b10 "
b10 $
#40
b1001 !
b1001 %
b100 &
b11 "
b11 $
#50
b10000 !
b10000 %
b101 &
b100 "
b100 $
#60
b11001 !
b11001 %
b110 &
b101 "
b101 $
#70
b100100 !
b100100 %
b111 &
b110 "
b110 $
#80
b110001 !
b110001 %
b1000 &
b111 "
b111 $
#90
b1000000 !
b1000000 %
b1001 &
b1000 "
b1000 $
#100
b1010001 !
b1010001 %
b1010 &
b1001 "
b1001 $
#110
b1100100 !
b1100100 %
b1011 &
b1010 "
b1010 $
#120
b1111001 !
b1111001 %
b1100 &
b1011 "
b1011 $
#130
b10010000 !
b10010000 %
b1101 &
b1100 "
b1100 $
#140
b10101001 !
b10101001 %
b1110 &
b1101 "
b1101 $
#150
b11000100 !
b11000100 %
b1111 &
b1110 "
b1110 $
#160
b11100001 !
b11100001 %
b10000 &
b1111 "
b1111 $
#170
b0 !
b0 %
1#
b0 "
b0 $
#190
b0 '
#200
b1 '
#210
b1 !
b1 %
b10 '
b1 "
b1 $
#220
b100 !
b100 %
b11 '
b10 "
b10 $
#230
b1001 !
b1001 %
b100 '
b11 "
b11 $
#240
b10000 !
b10000 %
b101 '
b100 "
b100 $
#250
b11001 !
b11001 %
b110 '
b101 "
b101 $
#260
b100100 !
b100100 %
b111 '
b110 "
b110 $
#270
b110001 !
b110001 %
b1000 '
b111 "
b111 $
#280
b1000000 !
b1000000 %
b1001 '
b1000 "
b1000 $
#290
b110001 !
b110001 %
b1010 '
b1001 "
b1001 $
#300
b100100 !
b100100 %
b1011 '
b1010 "
b1010 $
#310
b11001 !
b11001 %
b1100 '
b1011 "
b1011 $
#320
b10000 !
b10000 %
b1101 '
b1100 "
b1100 $
#330
b1001 !
b1001 %
b1110 '
b1101 "
b1101 $
#340
b100 !
b100 %
b1111 '
b1110 "
b1110 $
#350
b1 !
b1 %
b10000 '
b1111 "
b1111 $
