426 - VLSI SYSTEMS/LABS/LAB5/src/rom_b.v
/*
    Chase Lotito - SIUC
    ECE426 - Lab 5 - Design of Memory in Verilog
    Section B: ROM Square Root Circuit
        -> sq_root root unsigned 0-15
            -> provide 3 decimals
*/

module rom_b (n, sq_root);

// I/O
input [3:0] n;               // unsigned number
output reg [11:0] sq_root;   // answer = n**1/2

wire [1:0] sq_root_int;      // integer part of sq_root
wire [9:0] sq_root_dp;       // decimal part of sq_root

// procedural block to compute roots as inputs come in
always @ (n)
begin
    case (n)
        0 :sq_root <= 0;
        1 :sq_root <= {2'd1, 10'd0};
        2 :sq_root <= {2'd1, 10'd414};
        3 :sq_root <= {2'd1, 10'd732};
        4 :sq_root <= {2'd2, 10'd0};
        5 :sq_root <= {2'd2, 10'd236};
        6 :sq_root <= {2'd2, 10'd450};
        7 :sq_root <= {2'd2, 10'd646};
        8 :sq_root <= {2'd2, 10'd828};
        9 :sq_root <= {2'd3, 10'd0};
        10 :sq_root <= {2'd3, 10'd162};
        11 :sq_root <= {2'd3, 10'd317};
        12 :sq_root <= {2'd3, 10'd464};
        13 :sq_root <= {2'd3, 10'd606};
        14 :sq_root <= {2'd3, 10'd742};
        15 :sq_root <= {2'd3, 10'd873};
        default: sq_root <= 12'd0; // reset by default
    endcase
end

// continuous assignments for int and decimal parts
assign sq_root_int = sq_root [11:10];
assign sq_root_dp = sq_root [9:0];

endmodule

426 - VLSI SYSTEMS/LABS/LAB5/src/rom_b_tb.v
/*
    chase lotito
    lab 5 section a
    rom square root testbench
*/

`include "./rom_b.v"
`timescale 1us / 1us

module rom_b_tb();

// GTKWAVE (waveform simulator)
initial begin : GTKWAVE
    $dumpfile("rom_b.vcd");
    $dumpvars(0, rom_b_tb);
end

// I/O
reg [3:0] n;             // signed number
wire [11:0] sq_root;     // square root of n

// Initialize the Squarer ROM
rom_b U1 (
    .n(n), .sq_root(sq_root)
);

// Send 4-bit numbers 0000 -> 1111
initial begin : stimulus

    // n = 0000 -> 1111
    for(integer i = 0; i < 16; i = i + 1)
        #10 n = i;

    #10 $finish;
end


endmodule

426 - VLSI SYSTEMS/LABS/LAB5/src/rom_b.vcd
$date
	Fri Apr 19 22:19:42 2024
$end
$version
	Icarus Verilog
$end
$timescale
	1us
$end
$scope module rom_b_tb $end
$var wire 12 ! sq_root [11:0] $end
$var reg 4 " n [3:0] $end
$scope module U1 $end
$var wire 4 # n [3:0] $end
$var wire 2 $ sq_root_int [1:0] $end
$var wire 10 % sq_root_dp [9:0] $end
$var reg 12 & sq_root [11:0] $end
$upscope $end
$scope begin GTKWAVE $end
$upscope $end
$scope begin stimulus $end
$scope begin $ivl_for_loop0 $end
$var integer 32 ' i [31:0] $end
$upscope $end
$upscope $end
$upscope $end
$enddefinitions $end
$comment Show the parameter values. $end
$dumpall
$end
#0
$dumpvars
b0 '
bx &
bx %
bx $
bx #
bx "
bx !
$end
#10
b0 $
b0 %
b0 !
b0 &
b1 '
b0 "
b0 #
#20
b1 $
b10000000000 !
b10000000000 &
b10 '
b1 "
b1 #
#30
b110011110 %
b10110011110 !
b10110011110 &
b11 '
b10 "
b10 #
#40
b1011011100 %
b11011011100 !
b11011011100 &
b100 '
b11 "
b11 #
#50
b10 $
b0 %
b100000000000 !
b100000000000 &
b101 '
b100 "
b100 #
#60
b11101100 %
b100011101100 !
b100011101100 &
b110 '
b101 "
b101 #
#70
b111000010 %
b100111000010 !
b100111000010 &
b111 '
b110 "
b110 #
#80
b1010000110 %
b101010000110 !
b101010000110 &
b1000 '
b111 "
b111 #
#90
b1100111100 %
b101100111100 !
b101100111100 &
b1001 '
b1000 "
b1000 #
#100
b11 $
b0 %
b110000000000 !
b110000000000 &
b1010 '
b1001 "
b1001 #
#110
b10100010 %
b110010100010 !
b110010100010 &
b1011 '
b1010 "
b1010 #
#120
b100111101 %
b110100111101 !
b110100111101 &
b1100 '
b1011 "
b1011 #
#130
b111010000 %
b110111010000 !
b110111010000 &
b1101 '
b1100 "
b1100 #
#140
b1001011110 %
b111001011110 !
b111001011110 &
b1110 '
b1101 "
b1101 #
#150
b1011100110 %
b111011100110 !
b111011100110 &
b1111 '
b1110 "
b1110 #
#160
b1101101001 %
b111101101001 !
b111101101001 &
b10000 '
b1111 "
b1111 #
