426 - VLSI SYSTEMS/HW/HW5/q1/q1.v
// Chase Lotito - SIUC Undergraduate - Spring 2024
// ECE426 w/ Chao Lu
// HW5
// Q1: Design a Mealy-type FSM that cdan act as a sequence detector.

`timescale 1us / 1us

module mealyFSM (
    clk, reset, w, out
);

// I/O
input clk, reset, w;
output out;             // wire for continuous assignment

reg [1:0] present, next; // p for present-state, n for next-state

// Parameters for cases
// 3 cases, so lets use 2-bits
parameter A = 2'b01, B = 2'b10, C = 2'b11;  // we will count 1, 2, 3 
// Initial Conditions
initial begin
    present = A;
end

// Console log
always @ (w, out) begin
    $monitor("[PRESENT] = %d | [NEXT] = %d, w = %b | [OUTPUT] = %b \n", present, next, w, out);
end

// Next-State Combinational Logic
always @ (w, present) begin
    case (present)
        A: next = w ? C : B;
        B: next = w ? C : B;
        C: next = w ? C : B;
        default: next = 2'bxx;
    endcase
end

// Sequential Logic
// using posedge reset because not specified in problem statement.
always @ (posedge clk, posedge reset) begin
    if (reset == 1'b1)
        present <= A;
    else
        present <= next;
end

// Output Logic
assign out = ( (present == B) && (w == 1'b0) ) || ( (present == C) && (w == 1'b1) );

endmodule

426 - VLSI SYSTEMS/HW/HW5 (finished)/q1/tb.v
// Chase Lotito - SIUC Undergraduate - Spring 2024
// ECE426 w/ Chao Lu
// HW5
// testbench for Q1


`include "q1.v"
`timescale 1us / 1us

module testbench();

// GTKWAVE
initial begin : GTKWAVE
    $dumpfile("q1.vcd");
    $dumpvars(0, testbench);
end

// I/O
wire out;
reg reset, clk, w;

// Initial Conditions
initial begin : initalConditions
    clk = 0;
    reset = 0;
    w = 0;
end

// Clock
always begin
    #10 clk = ~clk;
end

// Stimulus
initial begin : Stimulus
    repeat(20)
        w = #10 ~w;

    reset <= #50 1'b1;
    #100 $finish;
end

// Instantiate the FSM
mealyFSM U1 (
    .clk(clk),
    .reset(reset),
    .w(w),
    .out(out)
);

endmodule

426 - VLSI SYSTEMS/HW/HW5 (finished)/q1/q1.vcd
$date
	Sun Mar 10 14:09:48 2024
$end
$version
	Icarus Verilog
$end
$timescale
	1us
$end
$scope module testbench $end
$var wire 1 ! out $end
$var reg 1 " clk $end
$var reg 1 # reset $end
$var reg 1 $ w $end
$scope module U1 $end
$var wire 1 " clk $end
$var wire 1 ! out $end
$var wire 1 # reset $end
$var wire 1 $ w $end
$var parameter 2 % A $end
$var parameter 2 & B $end
$var parameter 2 ' C $end
$var reg 2 ( next [1:0] $end
$var reg 2 ) present [1:0] $end
$upscope $end
$scope begin GTKWAVE $end
$upscope $end
$scope begin Stimulus $end
$upscope $end
$scope begin initalConditions $end
$upscope $end
$upscope $end
$enddefinitions $end
$comment Show the parameter values. $end
$dumpall
b11 '
b10 &
b1 %
$end
#0
$dumpvars
b1 )
b10 (
0$
0#
0"
0!
$end
#10
b10 )
b11 (
1$
1"
#20
1!
b10 (
0$
0"
#30
0!
b11 (
1$
1"
#40
1!
b10 (
0$
0"
#50
0!
b11 (
1$
1"
#60
1!
b10 (
0$
0"
#70
0!
b11 (
1$
1"
#80
1!
b10 (
0$
0"
#90
0!
b11 (
1$
1"
#100
1!
b10 (
0$
0"
#110
0!
b11 (
1$
1"
#120
1!
b10 (
0$
0"
#130
0!
b11 (
1$
1"
#140
1!
b10 (
0$
0"
#150
0!
b11 (
1$
1"
#160
1!
b10 (
0$
0"
#170
0!
b11 (
1$
1"
#180
1!
b10 (
0$
0"
#190
0!
b11 (
1$
1"
#200
1!
b10 (
0$
0"
#210
1"
#220
0"
#230
1"
#240
0"
#250
0!
b1 )
1#
1"
