426 - VLSI SYSTEMS/HW/HW5/q2/q2.v
// Chase Lotito - SIUC Undergraduate - Spring 2024
// ECE426 w/ Chao Lu
// HW5
// Q2: Code FSM from circuit diagram

`timescale 1us / 1us

// The FSM
module fsm(
    clk, z, x
);

// I/O
input clk, x;
output z;
reg A, B;

// Intermediate wires (w1 == x, w2 == B, A == A)
wire w4, w5, w6, w7, w8;

// -- Gate-Level Modelling --
// level 1
not not1(w5, x);
or or1(z, x, B);
nand nand1(w4, x, B);
nand nand2(w6, x, A);
// level 2
nand nand3(w7, B, w5, A);
// level 3
nand nand4(w8, w4, w7, w6);
//---------------------------
// -- DFFs ------------------
initial begin
    A = 0;
    B = 0;
end
always @ (posedge clk) begin
    A <= w8;
    B <= A;
end
// --------------------------
initial begin
    $monitor("[%0t us] x = %d, z = %b, w8 = %b, A = %b, B = %b", $time, x, z, w8, A, B);
end
endmodule

426 - VLSI SYSTEMS/HW/HW5 (finished)/q2/tb.v
// Chase Lotito - SIUC Undergraduate - Spring 2024
// ECE426 w/ Chao Lu
// HW5
// testbench for Q2
`include "q2.v"
`timescale 1us / 1us

module testbench();

// GTKWAVE
initial begin : GTKWAVE
    $dumpfile("q2.vcd");
    $dumpvars(0, testbench);
end

//--------------------------
// I/O
reg clk, x;
wire z;

// Initals
initial begin : initalConditions
   clk = 0;
   x = 0;
end

// CLOCK
always begin : clock
   #10 clk = ~clk;
end

// PROGRAM LIFETIME
initial begin : programLifeTime
    #100 $finish;
end

// STIMULUS
initial begin : stimmychecks
    repeat(20)
        x = #3 ~x;
end

// MODULE INSTANTIATION
fsm U1 (
    .clk(clk),
    .z(z),
    .x(x)
);

endmodule

426 - VLSI SYSTEMS/HW/HW5 (finished)/q2/q2.vcd
$date
	Sun Mar 10 19:18:17 2024
$end
$version
	Icarus Verilog
$end
$timescale
	1us
$end
$scope module testbench $end
$var wire 1 ! z $end
$var reg 1 " clk $end
$var reg 1 # x $end
$scope module U1 $end
$var wire 1 " clk $end
$var wire 1 $ w4 $end
$var wire 1 % w5 $end
$var wire 1 & w6 $end
$var wire 1 ' w7 $end
$var wire 1 ( w8 $end
$var wire 1 # x $end
$var wire 1 ! z $end
$var reg 1 ) A $end
$var reg 1 * B $end
$upscope $end
$scope begin GTKWAVE $end
$upscope $end
$scope begin clock $end
$upscope $end
$scope begin initalConditions $end
$upscope $end
$scope begin programLifeTime $end
$upscope $end
$scope begin stimmychecks $end
$upscope $end
$upscope $end
$enddefinitions $end
$comment Show the parameter values. $end
$dumpall
$end
#0
$dumpvars
0*
0)
0(
1'
1&
1%
1$
0#
0"
0!
$end
#3
0%
1!
1#
#6
1%
0!
0#
#9
0%
1!
1#
#10
1"
#12
1%
0!
0#
#15
0%
1!
1#
#18
1%
0!
0#
#20
0"
#21
0%
1!
1#
#24
1%
0!
0#
#27
0%
1!
1#
#30
1%
0!
0#
1"
#33
0%
1!
1#
#36
1%
0!
0#
#39
0%
1!
1#
#40
0"
#42
1%
0!
0#
#45
0%
1!
1#
#48
1%
0!
0#
#50
1"
#51
0%
1!
1#
#54
1%
0!
0#
#57
0%
1!
1#
#60
1%
0!
0#
0"
