426 - VLSI SYSTEMS/HW/HW2 (finished)/Q6/CircuitImplementation.v
/*
    Chase Lotito - SIUC - SP2024
    ECE426 - Chao Lu
    HW 2 - Q6 - Circuit Implementation
*/

module CircuitImplementation (
    Y, A, B, C, D
);

// I/O
input A, B, C, D;
output Y;

// Other connections
wire _D, na0, a0, xno0, o0, no0;

// Gate-Level Logic
not NOT0(_D, D);

nand NAND0(na0, A, B); // LEVEL 1
and AND0(a0, C, _D);

xnor XNOR0(xno0, na0, a0); // LEVEL 2

or OR0(o0, na0, xno0); // LEVEL 3
nor NOR0(no0, xno0, a0);

nor NOR1(Y, o0, no0); // OUTPUT

endmodule

426 - VLSI SYSTEMS/HW/HW2 (finished)/Q6/tb.v
/*
    Chase Lotito - SIUC - SP2024
    HW2- Q6 - Testbench
*/

`include "CircuitImplementation.v"
`timescale 1ns/1ns

module tb();

// I/O
reg [3:0] I;
wire Y;

// Module Instantiation!
CircuitImplementation U1 (
    .Y(Y), .A(I[0]), .B(I[1]), .C(I[2]), .D(I[3])
);

// GTKWAVE
initial begin : GTKWAVE
    $dumpfile("tb.vcd");
    $dumpvars(0, tb);
end

// Stimulus!
initial begin : STIMMYCHECKS
    reg [4:0] iv;

    // Assign input values 0 --> 15
    for(iv = 0; iv < 16; iv = iv + 1)
        #20 I = iv;
    
    #10 $finish; // end stimmy
end

// Monitor and Console Log
always @(Y) begin
    $monitor("{A, B, C, D} = {%b%b%b%b}, Y = %b", I[0], I[1], I[2], I[3], Y);
end

endmodule

426 - VLSI SYSTEMS/HW/HW2 (finished)/Q6/tb.vcd
$date
	Fri Feb 02 14:34:05 2024
$end
$version
	Icarus Verilog
$end
$timescale
	1ns
$end
$scope module tb $end
$var wire 1 ! Y $end
$var reg 4 " I [3:0] $end
$scope module U1 $end
$var wire 1 # A $end
$var wire 1 $ B $end
$var wire 1 % C $end
$var wire 1 & D $end
$var wire 1 ! Y $end
$var wire 1 ' _D $end
$var wire 1 ( a0 $end
$var wire 1 ) na0 $end
$var wire 1 * no0 $end
$var wire 1 + o0 $end
$var wire 1 , xno0 $end
$upscope $end
$scope begin GTKWAVE $end
$upscope $end
$scope begin STIMMYCHECKS $end
$var reg 5 - iv [4:0] $end
$upscope $end
$upscope $end
$enddefinitions $end
$comment Show the parameter values. $end
$dumpall
$end
#0
$dumpvars
b0 -
x,
x+
x*
x)
x(
x'
x&
x%
x$
x#
bx "
x!
$end
#20
0!
1*
1+
0,
1)
0(
1'
0#
0$
0%
0&
b1 -
b0 "
#40
1#
b10 -
b1 "
#60
0#
1$
b11 -
b10 "
#80
0*
1,
1+
0)
1#
b100 -
b11 "
#100
1)
1(
0#
0$
1%
b101 -
b100 "
#120
1#
b110 -
b101 "
#140
0#
1$
b111 -
b110 "
#160
1!
0+
0,
0)
1#
b1000 -
b111 "
#180
0!
1+
1*
1)
0(
0'
0#
0$
0%
1&
b1001 -
b1000 "
#200
1#
b1010 -
b1001 "
#220
0#
1$
b1011 -
b1010 "
#240
0*
1,
1+
0)
1#
b1100 -
b1011 "
#260
1*
0,
1)
0#
0$
1%
b1101 -
b1100 "
#280
1#
b1110 -
b1101 "
#300
0#
1$
b1111 -
b1110 "
#320
0*
1,
1+
0)
1#
b10000 -
b1111 "
