426 - VLSI SYSTEMS/HW/HW2 (finished)/Q4/EvenParityGenerator.v
// Chase Lotito - SIUC - SP2024
// ECE426 - Chao Lu
// HW2 - Q4 - Even Parity Generator

/*
    This approach is more ad hoc and not derived from a truth table
        1) An XNOR gate is high only for all low inputs or even high inputs
        2) Also send all inputs into OR gate to check if all zero
        3) Send out of XNOR and out of OR into AND to get both even
            and at least one input high!
*/

module EvenParityGenerator (
    OP, I
);
    
// I/O
input [7:0] I;
output OP;

// Intermediate wires
wire orOut; // output of OR gate
wire xnorOut; // output of XNOR gate

// Gate-Level Design
xnor XNOR(xnorOut, I[0], I[1], I[2], I[3], I[4], I[5], I[6], I[7]);
or OR(orOut, I[0], I[1], I[2], I[3], I[4], I[5], I[6], I[7]);
and AND(OP, orOut, xnorOut);


endmodule

426 - VLSI SYSTEMS/HW/HW2 (finished)/Q4/tb.v
// Lotito - Q4 Testbench

`include "EvenParityGenerator.v"
`timescale 1ns/1ns

module tb();

// I/O
reg [7:0] I;
wire OP;

// GTKWAVE 
initial begin
    $dumpfile("tb.vcd");
    $dumpvars(0,tb);
end

// Stimulus
initial begin : stimmychecks
   
    // loop through all 256 inputs!
    reg [8:0] iv;
    for(iv = 0; iv < 256; iv=iv+1)
       #10 I = iv;

    #10 $finish; // break!
end

// Monitor and log changes in input
always@(I)
    $monitor("I = {%b}, Parity: %b", I, OP);

// Initialize module
EvenParityGenerator U1 (
    .OP(OP), .I(I)
);

endmodule

426 - VLSI SYSTEMS/HW/HW2 (finished)/Q4/tb.vcd
$date
	Thu Feb 01 19:02:38 2024
$end
$version
	Icarus Verilog
$end
$timescale
	1ns
$end
$scope module tb $end
$var wire 1 ! OP $end
$var reg 8 " I [7:0] $end
$scope module U1 $end
$var wire 8 # I [7:0] $end
$var wire 1 ! OP $end
$var wire 1 $ orOut $end
$var wire 1 % xnorOut $end
$upscope $end
$scope begin stimmychecks $end
$var reg 9 & iv [8:0] $end
$upscope $end
$upscope $end
$enddefinitions $end
$comment Show the parameter values. $end
$dumpall
$end
#0
$dumpvars
b0 &
x%
x$
bx #
bx "
x!
$end
#10
0!
1%
0$
b1 &
b0 "
b0 #
#20
0%
1$
b10 &
b1 "
b1 #
#30
b11 &
b10 "
b10 #
#40
1!
1%
b100 &
b11 "
b11 #
#50
0!
0%
b101 &
b100 "
b100 #
#60
1!
1%
b110 &
b101 "
b101 #
#70
b111 &
b110 "
b110 #
#80
0!
0%
b1000 &
b111 "
b111 #
#90
b1001 &
b1000 "
b1000 #
#100
1!
1%
b1010 &
b1001 "
b1001 #
#110
b1011 &
b1010 "
b1010 #
#120
0!
0%
b1100 &
b1011 "
b1011 #
#130
1!
1%
b1101 &
b1100 "
b1100 #
#140
0!
0%
b1110 &
b1101 "
b1101 #
#150
b1111 &
b1110 "
b1110 #
#160
1!
1%
b10000 &
b1111 "
b1111 #
#170
0!
0%
b10001 &
b10000 "
b10000 #
#180
1!
1%
b10010 &
b10001 "
b10001 #
#190
b10011 &
b10010 "
b10010 #
#200
0!
0%
b10100 &
b10011 "
b10011 #
#210
1!
1%
b10101 &
b10100 "
b10100 #
#220
0!
0%
b10110 &
b10101 "
b10101 #
#230
b10111 &
b10110 "
b10110 #
#240
1!
1%
b11000 &
b10111 "
b10111 #
#250
b11001 &
b11000 "
b11000 #
#260
0!
0%
b11010 &
b11001 "
b11001 #
#270
b11011 &
b11010 "
b11010 #
#280
1!
1%
b11100 &
b11011 "
b11011 #
#290
0!
0%
b11101 &
b11100 "
b11100 #
#300
1!
1%
b11110 &
b11101 "
b11101 #
#310
b11111 &
b11110 "
b11110 #
#320
0!
0%
b100000 &
b11111 "
b11111 #
#330
b100001 &
b100000 "
b100000 #
#340
1!
1%
b100010 &
b100001 "
b100001 #
#350
b100011 &
b100010 "
b100010 #
#360
0!
0%
b100100 &
b100011 "
b100011 #
#370
1!
1%
b100101 &
b100100 "
b100100 #
#380
0!
0%
b100110 &
b100101 "
b100101 #
#390
b100111 &
b100110 "
b100110 #
#400
1!
1%
b101000 &
b100111 "
b100111 #
#410
b101001 &
b101000 "
b101000 #
#420
0!
0%
b101010 &
b101001 "
b101001 #
#430
b101011 &
b101010 "
b101010 #
#440
1!
1%
b101100 &
b101011 "
b101011 #
#450
0!
0%
b101101 &
b101100 "
b101100 #
#460
1!
1%
b101110 &
b101101 "
b101101 #
#470
b101111 &
b101110 "
b101110 #
#480
0!
0%
b110000 &
b101111 "
b101111 #
#490
1!
1%
b110001 &
b110000 "
b110000 #
#500
0!
0%
b110010 &
b110001 "
b110001 #
#510
b110011 &
b110010 "
b110010 #
#520
1!
1%
b110100 &
b110011 "
b110011 #
#530
0!
0%
b110101 &
b110100 "
b110100 #
#540
1!
1%
b110110 &
b110101 "
b110101 #
#550
b110111 &
b110110 "
b110110 #
#560
0!
0%
b111000 &
b110111 "
b110111 #
#570
b111001 &
b111000 "
b111000 #
#580
1!
1%
b111010 &
b111001 "
b111001 #
#590
b111011 &
b111010 "
b111010 #
#600
0!
0%
b111100 &
b111011 "
b111011 #
#610
1!
1%
b111101 &
b111100 "
b111100 #
#620
0!
0%
b111110 &
b111101 "
b111101 #
#630
b111111 &
b111110 "
b111110 #
#640
1!
1%
b1000000 &
b111111 "
b111111 #
#650
0!
0%
b1000001 &
b1000000 "
b1000000 #
#660
1!
1%
b1000010 &
b1000001 "
b1000001 #
#670
b1000011 &
b1000010 "
b1000010 #
#680
0!
0%
b1000100 &
b1000011 "
b1000011 #
#690
1!
1%
b1000101 &
b1000100 "
b1000100 #
#700
0!
0%
b1000110 &
b1000101 "
b1000101 #
#710
b1000111 &
b1000110 "
b1000110 #
#720
1!
1%
b1001000 &
b1000111 "
b1000111 #
#730
b1001001 &
b1001000 "
b1001000 #
#740
0!
0%
b1001010 &
b1001001 "
b1001001 #
#750
b1001011 &
b1001010 "
b1001010 #
#760
1!
1%
b1001100 &
b1001011 "
b1001011 #
#770
0!
0%
b1001101 &
b1001100 "
b1001100 #
#780
1!
1%
b1001110 &
b1001101 "
b1001101 #
#790
b1001111 &
b1001110 "
b1001110 #
#800
0!
0%
b1010000 &
b1001111 "
b1001111 #
#810
1!
1%
b1010001 &
b1010000 "
b1010000 #
#820
0!
0%
b1010010 &
b1010001 "
b1010001 #
#830
b1010011 &
b1010010 "
b1010010 #
#840
1!
1%
b1010100 &
b1010011 "
b1010011 #
#850
0!
0%
b1010101 &
b1010100 "
b1010100 #
#860
1!
1%
b1010110 &
b1010101 "
b1010101 #
#870
b1010111 &
b1010110 "
b1010110 #
#880
0!
0%
b1011000 &
b1010111 "
b1010111 #
#890
b1011001 &
b1011000 "
b1011000 #
#900
1!
1%
b1011010 &
b1011001 "
b1011001 #
#910
b1011011 &
b1011010 "
b1011010 #
#920
0!
0%
b1011100 &
b1011011 "
b1011011 #
#930
1!
1%
b1011101 &
b1011100 "
b1011100 #
#940
0!
0%
b1011110 &
b1011101 "
b1011101 #
#950
b1011111 &
b1011110 "
b1011110 #
#960
1!
1%
b1100000 &
b1011111 "
b1011111 #
#970
b1100001 &
b1100000 "
b1100000 #
#980
0!
0%
b1100010 &
b1100001 "
b1100001 #
#990
b1100011 &
b1100010 "
b1100010 #
#1000
1!
1%
b1100100 &
b1100011 "
b1100011 #
#1010
0!
0%
b1100101 &
b1100100 "
b1100100 #
#1020
1!
1%
b1100110 &
b1100101 "
b1100101 #
#1030
b1100111 &
b1100110 "
b1100110 #
#1040
0!
0%
b1101000 &
b1100111 "
b1100111 #
#1050
b1101001 &
b1101000 "
b1101000 #
#1060
1!
1%
b1101010 &
b1101001 "
b1101001 #
#1070
b1101011 &
b1101010 "
b1101010 #
#1080
0!
0%
b1101100 &
b1101011 "
b1101011 #
#1090
1!
1%
b1101101 &
b1101100 "
b1101100 #
#1100
0!
0%
b1101110 &
b1101101 "
b1101101 #
#1110
b1101111 &
b1101110 "
b1101110 #
#1120
1!
1%
b1110000 &
b1101111 "
b1101111 #
#1130
0!
0%
b1110001 &
b1110000 "
b1110000 #
#1140
1!
1%
b1110010 &
b1110001 "
b1110001 #
#1150
b1110011 &
b1110010 "
b1110010 #
#1160
0!
0%
b1110100 &
b1110011 "
b1110011 #
#1170
1!
1%
b1110101 &
b1110100 "
b1110100 #
#1180
0!
0%
b1110110 &
b1110101 "
b1110101 #
#1190
b1110111 &
b1110110 "
b1110110 #
#1200
1!
1%
b1111000 &
b1110111 "
b1110111 #
#1210
b1111001 &
b1111000 "
b1111000 #
#1220
0!
0%
b1111010 &
b1111001 "
b1111001 #
#1230
b1111011 &
b1111010 "
b1111010 #
#1240
1!
1%
b1111100 &
b1111011 "
b1111011 #
#1250
0!
0%
b1111101 &
b1111100 "
b1111100 #
#1260
1!
1%
b1111110 &
b1111101 "
b1111101 #
#1270
b1111111 &
b1111110 "
b1111110 #
#1280
0!
0%
b10000000 &
b1111111 "
b1111111 #
#1290
b10000001 &
b10000000 "
b10000000 #
#1300
1!
1%
b10000010 &
b10000001 "
b10000001 #
#1310
b10000011 &
b10000010 "
b10000010 #
#1320
0!
0%
b10000100 &
b10000011 "
b10000011 #
#1330
1!
1%
b10000101 &
b10000100 "
b10000100 #
#1340
0!
0%
b10000110 &
b10000101 "
b10000101 #
#1350
b10000111 &
b10000110 "
b10000110 #
#1360
1!
1%
b10001000 &
b10000111 "
b10000111 #
#1370
b10001001 &
b10001000 "
b10001000 #
#1380
0!
0%
b10001010 &
b10001001 "
b10001001 #
#1390
b10001011 &
b10001010 "
b10001010 #
#1400
1!
1%
b10001100 &
b10001011 "
b10001011 #
#1410
0!
0%
b10001101 &
b10001100 "
b10001100 #
#1420
1!
1%
b10001110 &
b10001101 "
b10001101 #
#1430
b10001111 &
b10001110 "
b10001110 #
#1440
0!
0%
b10010000 &
b10001111 "
b10001111 #
#1450
1!
1%
b10010001 &
b10010000 "
b10010000 #
#1460
0!
0%
b10010010 &
b10010001 "
b10010001 #
#1470
b10010011 &
b10010010 "
b10010010 #
#1480
1!
1%
b10010100 &
b10010011 "
b10010011 #
#1490
0!
0%
b10010101 &
b10010100 "
b10010100 #
#1500
1!
1%
b10010110 &
b10010101 "
b10010101 #
#1510
b10010111 &
b10010110 "
b10010110 #
#1520
0!
0%
b10011000 &
b10010111 "
b10010111 #
#1530
b10011001 &
b10011000 "
b10011000 #
#1540
1!
1%
b10011010 &
b10011001 "
b10011001 #
#1550
b10011011 &
b10011010 "
b10011010 #
#1560
0!
0%
b10011100 &
b10011011 "
b10011011 #
#1570
1!
1%
b10011101 &
b10011100 "
b10011100 #
#1580
0!
0%
b10011110 &
b10011101 "
b10011101 #
#1590
b10011111 &
b10011110 "
b10011110 #
#1600
1!
1%
b10100000 &
b10011111 "
b10011111 #
#1610
b10100001 &
b10100000 "
b10100000 #
#1620
0!
0%
b10100010 &
b10100001 "
b10100001 #
#1630
b10100011 &
b10100010 "
b10100010 #
#1640
1!
1%
b10100100 &
b10100011 "
b10100011 #
#1650
0!
0%
b10100101 &
b10100100 "
b10100100 #
#1660
1!
1%
b10100110 &
b10100101 "
b10100101 #
#1670
b10100111 &
b10100110 "
b10100110 #
#1680
0!
0%
b10101000 &
b10100111 "
b10100111 #
#1690
b10101001 &
b10101000 "
b10101000 #
#1700
1!
1%
b10101010 &
b10101001 "
b10101001 #
#1710
b10101011 &
b10101010 "
b10101010 #
#1720
0!
0%
b10101100 &
b10101011 "
b10101011 #
#1730
1!
1%
b10101101 &
b10101100 "
b10101100 #
#1740
0!
0%
b10101110 &
b10101101 "
b10101101 #
#1750
b10101111 &
b10101110 "
b10101110 #
#1760
1!
1%
b10110000 &
b10101111 "
b10101111 #
#1770
0!
0%
b10110001 &
b10110000 "
b10110000 #
#1780
1!
1%
b10110010 &
b10110001 "
b10110001 #
#1790
b10110011 &
b10110010 "
b10110010 #
#1800
0!
0%
b10110100 &
b10110011 "
b10110011 #
#1810
1!
1%
b10110101 &
b10110100 "
b10110100 #
#1820
0!
0%
b10110110 &
b10110101 "
b10110101 #
#1830
b10110111 &
b10110110 "
b10110110 #
#1840
1!
1%
b10111000 &
b10110111 "
b10110111 #
#1850
b10111001 &
b10111000 "
b10111000 #
#1860
0!
0%
b10111010 &
b10111001 "
b10111001 #
#1870
b10111011 &
b10111010 "
b10111010 #
#1880
1!
1%
b10111100 &
b10111011 "
b10111011 #
#1890
0!
0%
b10111101 &
b10111100 "
b10111100 #
#1900
1!
1%
b10111110 &
b10111101 "
b10111101 #
#1910
b10111111 &
b10111110 "
b10111110 #
#1920
0!
0%
b11000000 &
b10111111 "
b10111111 #
#1930
1!
1%
b11000001 &
b11000000 "
b11000000 #
#1940
0!
0%
b11000010 &
b11000001 "
b11000001 #
#1950
b11000011 &
b11000010 "
b11000010 #
#1960
1!
1%
b11000100 &
b11000011 "
b11000011 #
#1970
0!
0%
b11000101 &
b11000100 "
b11000100 #
#1980
1!
1%
b11000110 &
b11000101 "
b11000101 #
#1990
b11000111 &
b11000110 "
b11000110 #
#2000
0!
0%
b11001000 &
b11000111 "
b11000111 #
#2010
b11001001 &
b11001000 "
b11001000 #
#2020
1!
1%
b11001010 &
b11001001 "
b11001001 #
#2030
b11001011 &
b11001010 "
b11001010 #
#2040
0!
0%
b11001100 &
b11001011 "
b11001011 #
#2050
1!
1%
b11001101 &
b11001100 "
b11001100 #
#2060
0!
0%
b11001110 &
b11001101 "
b11001101 #
#2070
b11001111 &
b11001110 "
b11001110 #
#2080
1!
1%
b11010000 &
b11001111 "
b11001111 #
#2090
0!
0%
b11010001 &
b11010000 "
b11010000 #
#2100
1!
1%
b11010010 &
b11010001 "
b11010001 #
#2110
b11010011 &
b11010010 "
b11010010 #
#2120
0!
0%
b11010100 &
b11010011 "
b11010011 #
#2130
1!
1%
b11010101 &
b11010100 "
b11010100 #
#2140
0!
0%
b11010110 &
b11010101 "
b11010101 #
#2150
b11010111 &
b11010110 "
b11010110 #
#2160
1!
1%
b11011000 &
b11010111 "
b11010111 #
#2170
b11011001 &
b11011000 "
b11011000 #
#2180
0!
0%
b11011010 &
b11011001 "
b11011001 #
#2190
b11011011 &
b11011010 "
b11011010 #
#2200
1!
1%
b11011100 &
b11011011 "
b11011011 #
#2210
0!
0%
b11011101 &
b11011100 "
b11011100 #
#2220
1!
1%
b11011110 &
b11011101 "
b11011101 #
#2230
b11011111 &
b11011110 "
b11011110 #
#2240
0!
0%
b11100000 &
b11011111 "
b11011111 #
#2250
b11100001 &
b11100000 "
b11100000 #
#2260
1!
1%
b11100010 &
b11100001 "
b11100001 #
#2270
b11100011 &
b11100010 "
b11100010 #
#2280
0!
0%
b11100100 &
b11100011 "
b11100011 #
#2290
1!
1%
b11100101 &
b11100100 "
b11100100 #
#2300
0!
0%
b11100110 &
b11100101 "
b11100101 #
#2310
b11100111 &
b11100110 "
b11100110 #
#2320
1!
1%
b11101000 &
b11100111 "
b11100111 #
#2330
b11101001 &
b11101000 "
b11101000 #
#2340
0!
0%
b11101010 &
b11101001 "
b11101001 #
#2350
b11101011 &
b11101010 "
b11101010 #
#2360
1!
1%
b11101100 &
b11101011 "
b11101011 #
#2370
0!
0%
b11101101 &
b11101100 "
b11101100 #
#2380
1!
1%
b11101110 &
b11101101 "
b11101101 #
#2390
b11101111 &
b11101110 "
b11101110 #
#2400
0!
0%
b11110000 &
b11101111 "
b11101111 #
#2410
1!
1%
b11110001 &
b11110000 "
b11110000 #
#2420
0!
0%
b11110010 &
b11110001 "
b11110001 #
#2430
b11110011 &
b11110010 "
b11110010 #
#2440
1!
1%
b11110100 &
b11110011 "
b11110011 #
#2450
0!
0%
b11110101 &
b11110100 "
b11110100 #
#2460
1!
1%
b11110110 &
b11110101 "
b11110101 #
#2470
b11110111 &
b11110110 "
b11110110 #
#2480
0!
0%
b11111000 &
b11110111 "
b11110111 #
#2490
b11111001 &
b11111000 "
b11111000 #
#2500
1!
1%
b11111010 &
b11111001 "
b11111001 #
#2510
b11111011 &
b11111010 "
b11111010 #
#2520
0!
0%
b11111100 &
b11111011 "
b11111011 #
#2530
1!
1%
b11111101 &
b11111100 "
b11111100 #
#2540
0!
0%
b11111110 &
b11111101 "
b11111101 #
#2550
b11111111 &
b11111110 "
b11111110 #
#2560
1!
1%
b100000000 &
b11111111 "
b11111111 #
