426 - VLSI SYSTEMS/HW/HW2 (finished)/Q1/A/mux21_gate.v
// Chase Lotito - SIUC - ECE426 - HW 2
// Q1-A
    /*
        Use Verilog to describe the following 2:1 Multiplexer
        [GATE-LEVEL MODELING]
    */

module mux21_gate(SEL, A, B, OUT);

    // Initialize I/O
    input SEL, A, B;
    output OUT;

    // Intermediate Signals
    wire inv1, a1, a2;

    // Gate-Level Instantiation
    not INV (inv1, SEL);
    and AND1 (a1, A, inv1);
    and AND2 (a2, B, SEL);
    or OR2 (OUT, a1, a2);

endmodule

426 - VLSI SYSTEMS/HW/HW2 (finished)/Q1/A/tb.v
// Chase Lotito
// Testbench for Q1-A

`include "mux21_gate.v"
`timescale 1ns / 1ns

module tb();

// I/O
reg A, B, SEL;
wire OUT;

// GTKWAVE
initial begin : gtkwave
    $dumpfile("tb.vcd");
    $dumpvars(0,tb);
end


// Start-up
initial begin : stimies

    // Initialize counter
    reg [3:0] i;

    for (i = 0; i < 8; i = i + 1) begin
        {A, B, SEL} = i[3:0];
        
        // Display
        #10 $display("[MUX 2:1 INPUT]: A = %b, B = %b, SEL = %b", A, B, SEL);
    end
end

// Initialize module
mux21_gate U1 (

    .A(A),
    .B(B),
    .SEL(SEL)

);

endmodule

426 - VLSI SYSTEMS/HW/HW2 (finished)/Q1/A/tb.vcd
$date
	Thu Feb 01 00:33:21 2024
$end
$version
	Icarus Verilog
$end
$timescale
	1ns
$end
$scope module tb $end
$var reg 1 ! A $end
$var reg 1 " B $end
$var reg 1 # SEL $end
$scope module U1 $end
$var wire 1 ! A $end
$var wire 1 " B $end
$var wire 1 $ OUT $end
$var wire 1 # SEL $end
$var wire 1 % a1 $end
$var wire 1 & a2 $end
$var wire 1 ' inv1 $end
$upscope $end
$scope begin gtkwave $end
$upscope $end
$scope begin stimies $end
$var reg 4 ( i [3:0] $end
$upscope $end
$upscope $end
$enddefinitions $end
$comment Show the parameter values. $end
$dumpall
$end
#0
$dumpvars
b0 (
1'
0&
0%
0$
0#
0"
0!
$end
#10
0'
1#
b1 (
#20
1'
1"
0#
b10 (
#30
1$
0'
1&
1#
b11 (
#40
1%
1'
0&
1!
0"
0#
b100 (
#50
0$
0%
0'
1#
b101 (
#60
1$
1%
1'
1"
0#
b110 (
#70
0%
0'
1&
1#
b111 (
#80
b1000 (
