426 - VLSI SYSTEMS/LABS/LAB6/src/adder_b.v
// chase lotito - ece426 lab 6 - adder b
// Addition of two 16 bit, 2's complement nos., n1 and n2. 8 bits addition at a time. Result is 17 bits.

module adder_b ( clk, n1, n2, sum);

// i/o
input clk;
input [15:0] n1;
input [15:0] n2;
output [16:0] sum;

reg [16:0] sum;
wire [8:0] sum_LSB;
reg [8:0] sum_LSB_1;

reg [15:8] n1_reg1;
reg [15:8] n2_reg1;

wire [16:8] sum_MSB;
wire [16:0] sum_next;

assign sum_LSB = n1[7:0] + n2[7:0]; // Add least significant byte.sum_LSB [8] is the carry.

always @ (posedge clk)  // Pipeline 1, clk (1), register LSB to continue addition of MSB.
begin
    sum_LSB_1 <= sum_LSB;   // Preserve LSB sum
    n1_reg1 <= n1[15:8];    // Preserve MSBs
    n2_reg1 <= n2[15:8];
end

// Extend sign & add msbs with carry.
assign sum_MSB = {n1_reg1[15], n1_reg1[15:8]} + {n2_reg1[15], n2_reg1[15:8]} + sum_LSB_1 [8];// Add MSBs with carry.
assign sum_next = {sum_MSB, sum_LSB_1 [7:0]};

always @ (posedge clk)// Pipeline 2, clk (2), register result.
begin
    sum <= sum_next;
end

endmodule

426 - VLSI SYSTEMS/LABS/LAB6/src/adder_b_testbench.v
// chase lotito - ece426 adder_b testbench

`define CLKBYPERIOD2 5// Operate at 50 MHz.
`include "adder_b.v" // This is the design.

module adder_b_testbench;

reg clk;
reg [15:0] n1;
reg [15:0] n2;

wire [16:0] sum;

adder_b U1 (.clk(clk), .n1(n1), .n2(n2), .sum(sum) );

// GTKWAVE (waveform simulator)
initial begin : GTKWAVE
    $dumpfile("adder_b.vcd");
    $dumpvars(0, adder_b_testbench);
end

initial begin// Apply different sets of inputs.
 clk = 1'b0; n1 = 16'h0; n2 = 16'h0;

 #10 n1 = 16'h0001; n2 = 16'h0101;
 #10 n1 = 16'h0fff; n2 = 16'h0fff;
 #10 n1 = 16'h7fff; n2 = 16'h7fff;
 #10 n1 = 16'h8000; n2 = 16'h8000;
 #10 n1 = 16'h0001; n2 = 16'h0001;
 #10 n1 = 16'hffff; n2 = 16'h0001;
 #10 n1 = 16'h7fff; n2 = 16'h7fff;
 #10 n1 = 16'h5555; n2 = 16'haaaa;
 #10 n1 = 16'h0000; n2 = 16'h0000;

 #10 $stop;
 $finish;
end

initial $monitor("[%0t us] clk =%b n1 = %h n2 = %h sum = %h", $time, clk, n1, n2, sum);

always #`CLKBYPERIOD2 clk <= ~clk;// Toggle the clock.

endmodule

426 - VLSI SYSTEMS/LABS/LAB6/src/adder_b.vcd
$date
	Sat Apr 27 16:19:45 2024
$end
$version
	Icarus Verilog
$end
$timescale
	1s
$end
$scope module adder_b_testbench $end
$var wire 17 ! sum [16:0] $end
$var reg 1 " clk $end
$var reg 16 # n1 [15:0] $end
$var reg 16 $ n2 [15:0] $end
$scope module U1 $end
$var wire 1 " clk $end
$var wire 16 % n1 [15:0] $end
$var wire 16 & n2 [15:0] $end
$var wire 17 ' sum_next [16:0] $end
$var wire 9 ( sum_MSB [16:8] $end
$var wire 9 ) sum_LSB [8:0] $end
$var reg 8 * n1_reg1 [15:8] $end
$var reg 8 + n2_reg1 [15:8] $end
$var reg 17 , sum [16:0] $end
$var reg 9 - sum_LSB_1 [8:0] $end
$upscope $end
$scope begin GTKWAVE $end
$upscope $end
$upscope $end
$enddefinitions $end
$comment Show the parameter values. $end
$dumpall
$end
#0
$dumpvars
bx -
bx ,
bx +
bx *
b0 )
bx (
bx '
b0 &
b0 %
b0 $
b0 #
0"
bx !
$end
#5
b0 (
b0 '
b0 +
b0 *
b0 -
1"
#10
0"
b10 )
b100000001 $
b100000001 &
b1 #
b1 %
#15
b0 !
b0 ,
b100000010 '
b1 (
b1 +
b10 -
1"
#20
0"
b111111110 )
b111111111111 $
b111111111111 &
b111111111111 #
b111111111111 %
#25
b1111 +
b1111111111110 '
b11111 (
b1111 *
b111111110 -
b100000010 !
b100000010 ,
1"
#30
0"
b111111111111111 $
b111111111111111 &
b111111111111111 #
b111111111111111 %
#35
b1111111111110 !
b1111111111110 ,
b1111111 +
b1111111111111110 '
b11111111 (
b1111111 *
1"
#40
0"
b0 )
b1000000000000000 $
b1000000000000000 &
b1000000000000000 #
b1000000000000000 %
#45
b10000000 +
b10000000000000000 '
b100000000 (
b10000000 *
b0 -
b1111111111111110 !
b1111111111111110 ,
1"
#50
0"
b10 )
b1 $
b1 &
b1 #
b1 %
#55
b10000000000000000 !
b10000000000000000 ,
b0 +
b10 '
b0 (
b0 *
b10 -
1"
#60
0"
b100000000 )
b1111111111111111 #
b1111111111111111 %
#65
b0 '
b0 (
b11111111 *
b100000000 -
b10 !
b10 ,
1"
#70
0"
b111111110 )
b111111111111111 $
b111111111111111 &
b111111111111111 #
b111111111111111 %
#75
b0 !
b0 ,
b1111111 +
b1111111111111110 '
b11111111 (
b1111111 *
b111111110 -
1"
#80
0"
b11111111 )
b1010101010101010 $
b1010101010101010 &
b101010101010101 #
b101010101010101 %
#85
b10101010 +
b11111111111111111 '
b111111111 (
b1010101 *
b11111111 -
b1111111111111110 !
b1111111111111110 ,
1"
#90
0"
b0 )
b0 $
b0 &
b0 #
b0 %
#95
b11111111111111111 !
b11111111111111111 ,
b0 +
b0 '
b0 (
b0 *
b0 -
1"
