426 - VLSI SYSTEMS/LABS/LAB6/src/adder_a.v
// chase lotito - ece426 lab 6 - adder a

// Addition of two 16 bits, 2's complement nos., n1 and n2.  All the 16 bits addition at one stroke without any pipeline.
// Result is 17 bits.

`timescale 1us / 1us

module adder_a (clk, n1, n2, sum);

// i/o
input clk;
input [15:0] n1, n2;
output [16:0] sum ;

reg [16:0] sum;
wire [16:0] sum_i;

assign sum_i = {n1[15], n1} + {n2[15], n2};    // Add after sign extension - Result (i).

// Frequency of operation is not relevant since this is a combination circuit.
// Pipeline 1, clk (1), register final result (i).
always @ (posedge clk) begin
    sum <= sum_i;
end

endmodule

426 - VLSI SYSTEMS/LABS/LAB6/src/adder_a_testbench.v
// Test bench for adder_a design

`define CLKPERIODBY2 5 // Operate at 50 MHz.

`timescale 1us / 1us
`include "adder_a.v" // This is the design.

module adder_a_testbench;

reg clk;
reg [15:0] n1;
reg [15:0] n2;
wire [16:0] sum;

adder_a U1 (.clk(clk), .n1(n1), .n2(n2), .sum(sum) );

// GTKWAVE (waveform simulator)
initial begin : GTKWAVE
    $dumpfile("adder_a.vcd");
    $dumpvars(0, adder_a_testbench);
end

initial begin // Apply different sets of inputs.
    clk = 1'b0; n1 = 16'h0; n2 = 16'h0;

    #10 n1 = 16'h0001; n2 = 16'h0101;
    #10 n1 = 16'h0fff; n2 = 16'h0fff;
    #10 n1 = 16'h7fff; n2 = 16'h7fff;
    #10 n1 = 16'h8000; n2 = 16'h8000;
    #10 n1 = 16'h0001; n2 = 16'h0001;
    #10 n1 = 16'hffff; n2 = 16'h0001;
    #10 n1 = 16'h7fff; n2 = 16'h7fff;
    #10 n1 = 16'h5555; n2 = 16'haaaa;
    #10 n1 = 16'h0000; n2 = 16'h0000;

    #20 $finish;
end

initial $monitor("[%0t us] clk =%b n1 = %h n2 = %h sum = %h", $time, clk, n1, n2, sum);

always #`CLKPERIODBY2 clk <= ~clk;  // Toggle the clock.

endmodule

426 - VLSI SYSTEMS/LABS/LAB6/src/adder_a.vcd
$date
	Sat Apr 27 16:18:46 2024
$end
$version
	Icarus Verilog
$end
$timescale
	1us
$end
$scope module adder_a_testbench $end
$var wire 17 ! sum [16:0] $end
$var reg 1 " clk $end
$var reg 16 # n1 [15:0] $end
$var reg 16 $ n2 [15:0] $end
$scope module U1 $end
$var wire 1 " clk $end
$var wire 16 % n1 [15:0] $end
$var wire 16 & n2 [15:0] $end
$var wire 17 ' sum_i [16:0] $end
$var reg 17 ( sum [16:0] $end
$upscope $end
$scope begin GTKWAVE $end
$upscope $end
$upscope $end
$enddefinitions $end
$comment Show the parameter values. $end
$dumpall
$end
#0
$dumpvars
bx (
b0 '
b0 &
b0 %
b0 $
b0 #
0"
bx !
$end
#5
b0 !
b0 (
1"
#10
0"
b100000001 $
b100000001 &
b100000010 '
b1 #
b1 %
#15
b100000010 !
b100000010 (
1"
#20
0"
b111111111111 $
b111111111111 &
b1111111111110 '
b111111111111 #
b111111111111 %
#25
b1111111111110 !
b1111111111110 (
1"
#30
0"
b111111111111111 $
b111111111111111 &
b1111111111111110 '
b111111111111111 #
b111111111111111 %
#35
b1111111111111110 !
b1111111111111110 (
1"
#40
0"
b1000000000000000 $
b1000000000000000 &
b10000000000000000 '
b1000000000000000 #
b1000000000000000 %
#45
b10000000000000000 !
b10000000000000000 (
1"
#50
0"
b1 $
b1 &
b10 '
b1 #
b1 %
#55
b10 !
b10 (
1"
#60
0"
b0 '
b1111111111111111 #
b1111111111111111 %
#65
b0 !
b0 (
1"
#70
0"
b111111111111111 $
b111111111111111 &
b1111111111111110 '
b111111111111111 #
b111111111111111 %
#75
b1111111111111110 !
b1111111111111110 (
1"
#80
0"
b1010101010101010 $
b1010101010101010 &
b11111111111111111 '
b101010101010101 #
b101010101010101 %
#85
b11111111111111111 !
b11111111111111111 (
1"
#90
0"
b0 $
b0 &
b0 '
b0 #
b0 %
#95
b0 !
b0 (
1"
