426 - VLSI SYSTEMS/HW/HW2 (finished)/Q2/EIGHTBITBUFFER/eight_bit_buffer.v
// Chase Lotito - SIUC
// Q2
    // Tristate buffer with Primivitives
    // EIGHT BIT BUFFER

module EightBitBuffer ( E, I, D );
    
    // I/O
    input E;
    input [7:0] I;
    output [7:0] D;

    // Note I don't need intermediate wires!
    
    // Instantiate the buffers!
    bufif1 BUF0(D[0], I[0], E);
    bufif1 BUF1(D[1], I[1], E);
    bufif1 BUF2(D[2], I[2], E);
    bufif1 BUF3(D[3], I[3], E);
    bufif1 BUF4(D[4], I[4], E);
    bufif1 BUF5(D[5], I[5], E);
    bufif1 BUF6(D[6], I[6], E);
    bufif1 BUF7(D[7], I[7], E);

endmodule

426 - VLSI SYSTEMS/HW/HW2 (finished)/Q2/EIGHTBITBUFFER/tb.v
// Q2 Testbench

`include "eight_bit_buffer.v"
`timescale 1ns / 1ns

module tb();

// I/O
reg [7:0] I;
reg E;
wire [7:0] D;
integer i;

// GKTWAVE
initial begin : GKTWAVE
    $dumpfile("tb.vcd");
    $dumpvars(0,tb);
end

// Start-Up
initial begin : stimmichecks
    // Clear registers
    I = 8'h00;

    $display("EBB - EN OFF");
    // Test Cycle w/ ENABLE OFF
    for (i = 0; i < 8; i = i + 1) begin
        #10 I = 8'h00; // clear I
        E = 0;
        I[i] = 1;
        $display("I = %b, D = %b", I, D);
    end

    $display("EBB - EN ON");
    // Test Cycle w/ ENABLE ON
    for (i = 0; i < 7; i = 1 + i) begin
        #10 I = 8'h00; // clear I
        E = 1;
        I[i] = 1;
        $monitor("I = %b, D = %b", I, D); //$display caused lagging, just print when signal changes
    end
end

// Instantiate Buffer
EightBitBuffer U1 (

    .E(E),
    .I(I),
    .D(D)

);

endmodule

426 - VLSI SYSTEMS/HW/HW2 (finished)/Q2/EIGHTBITBUFFER/tb.vcd
$date
	Thu Feb 01 18:15:02 2024
$end
$version
	Icarus Verilog
$end
$timescale
	1ns
$end
$scope module tb $end
$var wire 8 ! D [7:0] $end
$var reg 1 " E $end
$var reg 8 # I [7:0] $end
$var integer 32 $ i [31:0] $end
$scope module U1 $end
$var wire 1 " E $end
$var wire 8 % I [7:0] $end
$var wire 8 & D [7:0] $end
$upscope $end
$scope begin GKTWAVE $end
$upscope $end
$scope begin stimmichecks $end
$upscope $end
$upscope $end
$enddefinitions $end
$comment Show the parameter values. $end
$dumpall
$end
#0
$dumpvars
bx &
b0 %
b0 $
b0 #
x"
bx !
$end
#10
b1 $
b1 #
b1 %
bz !
bz &
0"
#20
b10 $
b10 #
b10 %
#30
b11 $
b100 #
b100 %
#40
b100 $
b1000 #
b1000 %
#50
b101 $
b10000 #
b10000 %
#60
b110 $
b100000 #
b100000 %
#70
b111 $
b1000000 #
b1000000 %
#80
b0 $
b10000000 #
b10000000 %
#90
b1 $
b1 !
b1 &
1"
b1 #
b1 %
#100
b10 !
b10 &
b10 $
b10 #
b10 %
#110
b100 !
b100 &
b11 $
b100 #
b100 %
#120
b1000 !
b1000 &
b100 $
b1000 #
b1000 %
#130
b10000 !
b10000 &
b101 $
b10000 #
b10000 %
#140
b100000 !
b100000 &
b110 $
b100000 #
b100000 %
#150
b1000000 !
b1000000 &
b111 $
b1000000 #
b1000000 %
