426 - VLSI SYSTEMS/HW/HW2 (finished)/Q1/B/mux21_continuous.v
// Chase Lotito
// Q1-B
    // 2:1 Multiplexer with Continuous Assignment Statements

module mux21_continuous( SEL, A, B, OUT );
    // I/O
    input SEL, A, B;
    output OUT;

    // Continuous Assignment Approach
    assign OUT = (~SEL & A) | (SEL & B );
endmodule

426 - VLSI SYSTEMS/HW/HW2 (finished)/Q1/B/tb.v
// Chase Lotito
// Testbench for Q1-B

`include "mux21_continuous.v"
`timescale 1ns / 1ns

module tb();

// I/O
reg A, B, SEL;
wire OUT;

// GTKWAVE
initial begin : gtkwave
    $dumpfile("tb.vcd");
    $dumpvars(0,tb);
end


// Start-up
initial begin : stimies

    // Initialize counter
    reg [3:0] i;

    for (i = 0; i < 8; i = i + 1) begin
        {A, B, SEL} = i[3:0];
        
        // Display
        #10 $display("[MUX 2:1 INPUT]: A = %b, B = %b, SEL = %b", A, B, SEL);
    end
end

// Initialize module
mux21_continuous U1 (

    .A(A),
    .B(B),
    .SEL(SEL)

);

endmodule

426 - VLSI SYSTEMS/HW/HW2 (finished)/Q1/B/tb.vcd
$date
	Thu Feb 01 00:47:52 2024
$end
$version
	Icarus Verilog
$end
$timescale
	1ns
$end
$scope module tb $end
$var reg 1 ! A $end
$var reg 1 " B $end
$var reg 1 # SEL $end
$scope module U1 $end
$var wire 1 ! A $end
$var wire 1 " B $end
$var wire 1 $ OUT $end
$var wire 1 # SEL $end
$upscope $end
$scope begin gtkwave $end
$upscope $end
$scope begin stimies $end
$var reg 4 % i [3:0] $end
$upscope $end
$upscope $end
$enddefinitions $end
$comment Show the parameter values. $end
$dumpall
$end
#0
$dumpvars
b0 %
0$
0#
0"
0!
$end
#10
1#
b1 %
#20
1"
0#
b10 %
#30
1$
1#
b11 %
#40
1!
0"
0#
b100 %
#50
0$
1#
b101 %
#60
1$
1"
0#
b110 %
#70
1#
b111 %
#80
b1000 %
