426 - VLSI SYSTEMS/EXAMPREP/exam1/q2/q2.v
// Chase Lotito - SIUC - SP2024
// ECE426 Midterm Review - Q2
// Q2: Complete the behavioral description in Verilog for a synchronous 4-bit counter

// Requirements
//    1) Synchronous
//    2) 4-bit counter
//    3) When RESET = 0, Q is set to 0 at next rising-edge clock
//    4) When Q = 14, reset Q = 0 at next rising-edge clock

module counter (CLK, Q, RESET);

// I/O
input RESET, CLK;
output [3:0] Q;
reg [3:0] Q;

always @ (posedge CLK or RESET) begin
  if (RESET == 1'b0) begin
    while(CLK != 1'b1) begin
      // literally just wait
    end
    Q = 0;
      
  end
  else if (Q == 14)
    Q <= 0;
  else
    Q <= Q + 1;
end

endmodule

426 - VLSI SYSTEMS/EXAMPREP/exam1/q2/q2tb.v
// Q1 Testbench

`include "q2.v"
`timescale 1us / 1us

module q2tb();

// GTKWAVE
initial begin : GTKWAVE
  $dumpfile("q2tb.vcd");
  $dumpvars(0, q2tb);
end

// I/O
reg RESET, CLK;
wire [3:0] Q;

// Initial conditions

initial begin: initials
  RESET <= 1'b1;
  CLK <= 1'b0;
end

// CLK
always #10 CLK = ~CLK;

initial begin : stimmychecks
  RESET <= #15 1'b0;
  RESET <= #20 1'b1;
  RESET <= #115 1'b0;
  RESET <= #120 1'b1;
  #500 $finish;
end

// Instantiate module
counter U1 (
  .CLK(CLK),
  .Q(Q),
  .RESET(RESET)
);

endmodule

426 - VLSI SYSTEMS/EXAMPREP/exam1/q2/q2tb.vcd
$date
	Thu Feb 22 13:22:40 2024
$end
$version
	Icarus Verilog
$end
$timescale
	1us
$end
$scope module q2tb $end
$var wire 4 ! Q [3:0] $end
$var reg 1 " CLK $end
$var reg 1 # RESET $end
$scope module U1 $end
$var wire 1 " CLK $end
$var wire 1 # RESET $end
$var reg 4 $ Q [3:0] $end
$upscope $end
$scope begin GTKWAVE $end
$upscope $end
$scope begin initials $end
$upscope $end
$scope begin stimmychecks $end
$upscope $end
$upscope $end
$enddefinitions $end
$comment Show the parameter values. $end
$dumpall
$end
#0
$dumpvars
bx $
1#
0"
bx !
$end
#10
1"
#15
b0 !
b0 $
0#
#20
b1 !
b1 $
1#
0"
#30
b10 !
b10 $
1"
#40
0"
#50
b11 !
b11 $
1"
#60
0"
#70
b100 !
b100 $
1"
#80
0"
#90
b101 !
b101 $
1"
#100
0"
#110
b110 !
b110 $
1"
#115
b0 !
b0 $
0#
#120
b1 !
b1 $
1#
0"
#130
b10 !
b10 $
1"
#140
0"
#150
b11 !
b11 $
1"
#160
0"
#170
b100 !
b100 $
1"
#180
0"
#190
b101 !
b101 $
1"
#200
0"
#210
b110 !
b110 $
1"
#220
0"
#230
b111 !
b111 $
1"
#240
0"
#250
b1000 !
b1000 $
1"
#260
0"
#270
b1001 !
b1001 $
1"
#280
0"
#290
b1010 !
b1010 $
1"
#300
0"
#310
b1011 !
b1011 $
1"
#320
0"
#330
b1100 !
b1100 $
1"
#340
0"
#350
b1101 !
b1101 $
1"
#360
0"
#370
b1110 !
b1110 $
1"
#380
0"
#390
b0 !
b0 $
1"
#400
0"
#410
b1 !
b1 $
1"
#420
0"
#430
b10 !
b10 $
1"
#440
0"
#450
b11 !
b11 $
1"
#460
0"
#470
b100 !
b100 $
1"
#480
0"
#490
b101 !
b101 $
1"
