426 - VLSI SYSTEMS/HW/HW3 (finished)/Q2/q2.v
// Lotito - ECE426 HW3 - Q2
// Timing diagrams with initial and always blocks

`timescale 1us/1us

module q2 (

);

initial begin : GTKWAVE
    $dumpfile("q2.vcd");
    $dumpvars(0, q2);
end

reg test_pattern;
parameter idle = 300;

initial begin 
    #1000 $finish;
end

always begin
    test_pattern <= 1;
    test_pattern <= #20 0;
    test_pattern <= #50 1;
    test_pattern <= #90 0;
    test_pattern <= #140 1;
    test_pattern <= #200 0;
    #idle;

end

endmodule

426 - VLSI SYSTEMS/HW/HW3 (finished)/Q2/q2.vcd
$date
	Sun Feb 11 18:09:37 2024
$end
$version
	Icarus Verilog
$end
$timescale
	1us
$end
$scope module q2 $end
$var parameter 32 ! idle $end
$var reg 1 " test_pattern $end
$scope begin GTKWAVE $end
$upscope $end
$upscope $end
$enddefinitions $end
$comment Show the parameter values. $end
$dumpall
b100101100 !
$end
#0
$dumpvars
1"
$end
#20
0"
#50
1"
#90
0"
#140
1"
#200
0"
#300
1"
#320
0"
#350
1"
#390
0"
#440
1"
#500
0"
#600
1"
#620
0"
#650
1"
#690
0"
#740
1"
#800
0"
#900
1"
#920
0"
#950
1"
#990
0"
