426 - VLSI SYSTEMS/LABS/LAB5/example/rom_a.v
// This ROM stores the square of a number n. 

module rom_a (n, sign, square); 

input [3:0] n ;	  // Signed number.

input sign ;	 // Signed number if it is high and unsigned otherwise. 

output [7:0] square ;		// Result = n x n.

reg [7:0] square ;

always @ (n or sign)

begin

if (sign == 0)	// Output "square" if the input is unsigned. 

   begin

   case (n)

  		0 :	square <= 0 ;  
  		1 :	square <= 1 ;  
  		2 :	square <= 4 ;  
  		3 :	square <= 9 ; 
  		4 :	square <= 16 ;  
  		5 :	square <= 25 ;  
  		6 :	square <= 36 ; 
  		7 :	square <= 49 ;  
  		8 :	square <= 64 ;  
  		9 :	square <= 81 ;  
  		10 :	square <= 100 ;  
  		11 :	square <= 121 ; 
  		12 :	square <= 144 ;  
  		13 :	square <= 169 ;  
  		14 :	square <= 196 ; 
  		15 :	square <= 225 ;  


		default :	square <= 0 ;	// Clear the result.

    endcase

    end

else

   begin

   case (n)	// Output "square" if the input is signed. 

  		0 :	square <= 0 ;  
  		1 :	square <= 1 ;  
  		2 :	square <= 4 ;  
  		3 :	square <= 9 ; 
  		4 :	square <= 16 ;  
  		5 :	square <= 25 ;  
  		6 :	square <= 36 ; 
  		7 :	square <= 49 ;  
  		8 :	square <= 64 ;  
  		9 :	square <= 49 ;  
  		10 :	square <= 36 ;  
  		11 :	square <= 25 ; 
  		12 :	square <= 16 ;  
  		13 :	square <= 9 ;  
  		14 :	square <= 4 ; 
  		15 :	square <= 1 ;  

		default :	square <= 0 ;	// Clear the result.

    endcase

    end

end

endmodule

426 - VLSI SYSTEMS/LABS/LAB5/example/rom_a_testbench.v
// Test Bench for ROM based Squaring Circuit 

`include "rom_a.v"  			// Design.

module rom_a_test ; 

reg     [3:0] 	n ;
reg 	sign ;
wire	[7:0] 	square ;

rom_a  u1 (   // Invoke the design.
             .n(n),
             .sign(sign),
             .square(square)

            ); 

integer count ;

initial begin : GTKWAVE
    $dumpfile("rom_a.vcd");
    $dumpvars(0, rom_a_test);
end

initial 

begin

  #7 	sign = 0 ;

for (count = 0; count <17; count = count+1)	// Apply inputs in the range: 0 to +15, every 10 ns.

  #10 n = count ; 

  #10 sign = 1 ;
								// or
for (count = 0; count <17; count = count+1)	// apply inputs in the range: -8 to +7, every 10 ns.

  #10 n = count ; 

  #200

  $stop ;

end


initial

	$monitor($time, " ns  n = %b sign = %b  square = %b", n, sign, square);

endmodule

426 - VLSI SYSTEMS/LABS/LAB5/example/rom_a.vcd
$date
	Fri Apr 19 20:11:54 2024
$end
$version
	Icarus Verilog
$end
$timescale
	1s
$end
$scope module rom_a_test $end
$var wire 8 ! square [7:0] $end
$var reg 4 " n [3:0] $end
$var reg 1 # sign $end
$var integer 32 $ count [31:0] $end
$scope module u1 $end
$var wire 4 % n [3:0] $end
$var wire 1 # sign $end
$var reg 8 & square [7:0] $end
$upscope $end
$scope begin GTKWAVE $end
$upscope $end
$upscope $end
$enddefinitions $end
$comment Show the parameter values. $end
$dumpall
$end
#0
$dumpvars
bx &
bx %
bx $
x#
bx "
bx !
$end
#7
b0 !
b0 &
b0 $
0#
#17
b1 $
b0 "
b0 %
#27
b1 !
b1 &
b10 $
b1 "
b1 %
#37
b100 !
b100 &
b11 $
b10 "
b10 %
#47
b1001 !
b1001 &
b100 $
b11 "
b11 %
#57
b10000 !
b10000 &
b101 $
b100 "
b100 %
#67
b11001 !
b11001 &
b110 $
b101 "
b101 %
#77
b100100 !
b100100 &
b111 $
b110 "
b110 %
#87
b110001 !
b110001 &
b1000 $
b111 "
b111 %
#97
b1000000 !
b1000000 &
b1001 $
b1000 "
b1000 %
#107
b1010001 !
b1010001 &
b1010 $
b1001 "
b1001 %
#117
b1100100 !
b1100100 &
b1011 $
b1010 "
b1010 %
#127
b1111001 !
b1111001 &
b1100 $
b1011 "
b1011 %
#137
b10010000 !
b10010000 &
b1101 $
b1100 "
b1100 %
#147
b10101001 !
b10101001 &
b1110 $
b1101 "
b1101 %
#157
b11000100 !
b11000100 &
b1111 $
b1110 "
b1110 %
#167
b11100001 !
b11100001 &
b10000 $
b1111 "
b1111 %
#177
b0 !
b0 &
b10001 $
b0 "
b0 %
#187
b0 $
1#
#197
b1 $
#207
b1 !
b1 &
b10 $
b1 "
b1 %
#217
b100 !
b100 &
b11 $
b10 "
b10 %
#227
b1001 !
b1001 &
b100 $
b11 "
b11 %
#237
b10000 !
b10000 &
b101 $
b100 "
b100 %
#247
b11001 !
b11001 &
b110 $
b101 "
b101 %
#257
b100100 !
b100100 &
b111 $
b110 "
b110 %
#267
b110001 !
b110001 &
b1000 $
b111 "
b111 %
#277
b1000000 !
b1000000 &
b1001 $
b1000 "
b1000 %
#287
b110001 !
b110001 &
b1010 $
b1001 "
b1001 %
#297
b100100 !
b100100 &
b1011 $
b1010 "
b1010 %
#307
b11001 !
b11001 &
b1100 $
b1011 "
b1011 %
#317
b10000 !
b10000 &
b1101 $
b1100 "
b1100 %
#327
b1001 !
b1001 &
b1110 $
b1101 "
b1101 %
#337
b100 !
b100 &
b1111 $
b1110 "
b1110 %
#347
b1 !
b1 &
b10000 $
b1111 "
b1111 %
#357
b0 !
b0 &
b10001 $
b0 "
b0 %
